layers/__init__.py
layers/hybrid_layer.py
layers/ssma_layer.py
ssma-0.1.0.dist-info/METADATA
ssma-0.1.0.dist-info/WHEEL
ssma-0.1.0.dist-info/top_level.txt
ssma-0.1.0.dist-info/RECORD
